{
  "Source": "solidot",
  "Title": "北京试点数字墓园",
  "Link": "https://www.solidot.org/story?sid=75834",
  "Content": "\u003cdiv class=\"p_mainnew\"\u003e\n\t\t\t\t\t面对人口老龄化和土地稀缺，北京正在试点数字墓园。按照一座传统双穴墓的面积是 0.8 平方米来计算，算上道路等公摊面积，一亩地大约只能设计 200 个墓位。而一座 20 多平方米的数字安葬厅，就可以设置 150 余个墓位。在人去世火化之后，骨灰盒被放置在专门的格位上，每个墓位可以安放两个骨灰盒。每个数字墓位上都有一块电子屏，可以播放逝者的音容笑貌，甚至还引进了AR、VR 技术，与家属互动。全北京 5 座数字墓园共设有近 7000 个墓位。与传统墓位相比，数字墓位的租期同样是 20 年，价位在 3 万元到 10 万元之间。\n\u003cp\u003e\u003c/p\u003e\n\u003c!--more--\u003e\n\u003cp\u003e\u003c/p\u003e\n\u003cbr/\u003e\nhttps://slashdot.org/story/23/08/17/1325211/china-pilots-digital-burials-and-funeral-services-as-population-ages\u003cbr/\u003e\nhttps://www.beijing.gov.cn/fuwu/bmfw/sy/jrts/202304/t20230407_2991677.html\t\t\t\t\t                \u003c/div\u003e",
  "Date": "2023-08-18T08:41:44Z",
  "Author": "Wilson"
}