{
  "Source": "solidot",
  "Title": "苹果允许开发者向客户提供其它支付选项",
  "Link": "https://www.solidot.org/story?sid=69350",
  "Content": "\u003cdiv class=\"p_mainnew\"\u003e\n\t\t\t\t\t苹果\u003ca href=\"https://developer.apple.com/cn/news/?id=4m3f5hbw\" target=\"_blank\"\u003e\u003cu\u003e更新\u003c/u\u003e\u003c/a\u003e了它的《App Store 审核指南》，删除了“开发者不得使用从 app 内获得的信息将个人用户定向到 app 之外的位置，以使用 app 内购买项目之外的购买方式 (例如，个人用户在 app 内注册帐户后，向这位用户发送介绍其他购买方式的电子邮件)。”苹果是在 8 月份\u003ca href=\"https://www.solidot.org/story?sid=68709\"\u003e\u003cu\u003e宣布\u003c/u\u003e\u003c/a\u003e它允许应用开发者为客户提供无需支付佣金的直接购买方式。剔除相关条款兑现了这一声明。\t\t\t\t\t                \u003c/div\u003e",
  "Date": "2021-10-23T07:44:09Z",
  "Author": "WinterIsComing"
}