{
  "Source": "solidot",
  "Title": "YouTube 超过 Netflix 成为美国青少年主要的视频来源",
  "Link": "https://www.solidot.org/story?sid=76330",
  "Content": "\u003cdiv class=\"p_mainnew\"\u003e\n\t\t\t\t\t投行 Piper Sandler 的一项调查发现，美国青少年在 YouTube 上观看的视频时长超过了 Netflix。YouTube 占到了青少年每天视频消费时间总长的 29.1%，超过了 Netflix 的 28.7%。自春季以来，青少年 在YouTube 上的视频消费时间增加了一个百分点，而 Netflix 下降了逾两个百分点。调查结果凸显了流媒体业务的竞争激烈，以及 YouTube 作为免费视频网站的有利地位。Netflix 是付费订阅服务。\n\n\n\u003cp\u003e\u003c/p\u003e\n\u003c!--more--\u003e\n\u003cp\u003e\u003c/p\u003e\n\u003cbr/\u003e\nhttps://news.slashdot.org/story/23/10/12/0112244/youtube-passes-netflix-as-top-video-source-for-teens\t\t\t\t\t                \u003c/div\u003e",
  "Date": "2023-10-13T08:18:23Z",
  "Author": "Wilson"
}