{
  "Source": "solidot",
  "Title": "IPv6 普及度突破 32%",
  "Link": "https://www.solidot.org/story?sid=64526",
  "Content": "\u003cdiv class=\"p_mainnew\"\u003e\n\t\t\t\t\t根据 Google 的\u003ca href=\"https://tech.slashdot.org/story/20/05/30/0412238/ipv6-adoption-hits-32-will-stats-show-how-many-returned-to-the-office\"\u003e\u003cu\u003e统计\u003c/u\u003e\u003c/a\u003e，全球的 IPv6 普及度突破了 32%。按国别统计，中国只有 0.24%，美国 42%，加拿大 27.8%，俄罗斯 3.82%，印度 46%。因为移动网络、家庭宽带和企业网络在普及 IPv6 上的差异，当人们在工作时，统计数据会显示 IPv6 普及度出现下降，原因是移动网络和家庭宽带比企业网络更快普及 IPv6，而当人们在家远程办公时，普及度下跌幅度有所收窄，这种统计也能观察到企业的\u003ca href=\"https://tech.slashdot.org/story/20/05/30/0412238/ipv6-adoption-hits-32-will-stats-show-how-many-returned-to-the-office\"\u003e\u003cu\u003e复工情况\u003c/u\u003e\u003c/a\u003e。\t\t\t\t\t                \u003c/div\u003e",
  "Date": "2020-05-31T13:05:45Z",
  "Author": "WinterIsComing"
}