{
  "Source": "solidot",
  "Title": "Twitter 要求品牌商至少每月花 1000 美元广告费否则可能失去认证身份",
  "Link": "https://www.solidot.org/story?sid=75629",
  "Content": "\u003cdiv class=\"p_mainnew\"\u003e\n\t\t\t\t\tTwitter 或者 X 公司本周发送的邮件显示，品牌商每月至少需要花费 1000 美元在广告上，否则他们将面临失去身份认证。马斯克（Elon Mus）此前承认 Twitter 的广告收入下降了五成。为了增加收入，Twitter 开始对广告商采取更强硬的立场：从 8 月 7 日起，如果品牌账户过去 30 天内没有花费至少 1000 美元广告费，或者过去 180 天内没有花费 6000 美元广告费，那么他们的账户将失去金色勾选验证。马斯克称这项政策有助于减少骗子在其平台上创建数以百万计的账号。\n\n\n\n\u003cp\u003e\u003c/p\u003e\n\u003c!--more--\u003e\n\u003cp\u003e\u003c/p\u003e\n\u003cbr/\u003e\nhttps://www.wsj.com/articles/elon-musks-rebranded-twitter-cuts-ad-prices-d2615d8f\t\t\t\t\t                \u003c/div\u003e",
  "Date": "2023-07-27T05:35:52Z",
  "Author": "Wilson"
}