{
  "Source": "solidot",
  "Title": "阿里巴巴 2022 年员工总数下降 1.9 万",
  "Link": "https://www.solidot.org/story?sid=74224",
  "Content": "\u003cdiv class=\"p_mainnew\"\u003e\n\t\t\t\t\t阿里巴巴周四公布了截至 2022 年 12 月 31 日的季度财报，透露过去一年员工总数下降了 1.9 万，其中该\n季度裁员逾 4 千人。阿里巴巴此前披露它有逾 24 万员工。阿里巴巴裁员旨在削减成本应对全球经济寒冷。过去一年最大规模的裁员发生在夏天，当时阿里巴巴报告了上市以来首次收入下降。\n\u003cp\u003e\u003c/p\u003e\n\u003c!--more--\u003e\n\u003cp\u003e\u003c/p\u003e\n\u003cbr/\u003e\nhttps://data.alibabagroup.com/ecms-files/1508695866/b98f644d-8367-466e-9882-f3d87fa94026/December%20Quarter%202022%20Results.pdf\t\t\t\t\t                \u003c/div\u003e",
  "Date": "2023-02-24T06:15:13Z",
  "Author": "Wilson"
}