{
  "Source": "solidot",
  "Title": "男子内脏发现酵母菌令他喝什么都会醉",
  "Link": "https://www.solidot.org/story?sid=62385",
  "Content": "\u003cdiv class=\"p_mainnew\"\u003e\n\t\t\t\t\t研究人员在《BMJ Open Gastroenterology》期刊上\u003ca href=\"https://bmjopengastro.bmj.com/content/6/1/e000325\"\u003e\u003cu\u003e报告了\u003c/u\u003e\u003c/a\u003e一种罕见的疾病——自动酿酒综合症（Auto-Brewery Syndrome，ABS）。一名美国北卡男子在 2011 年 1 月因为严重的拇指创伤而接受了三周的抗生素治疗以对抗感染。他开始在就餐之后出现情绪低落的问题。2014 年他因为酒驾被捕，其血液中的酒精含量达到 0.2%（超过 0.08% 就受法律限制了）。他否认酒驾，但医院工作人员和警察都不相信他。他的一位亲戚在看过类似病例之后劝说他去就医。研究人员之后在其排泄物中发现了酵母菌，观察到他在食用碳水化合物之后血液酒精含量上升。\u003ca href=\"https://arstechnica.com/science/2019/10/man-charged-with-dwi-after-alcohol-fermenting-yeast-in-his-gut-got-him-wasted/\" target=\"_blank\"\u003e\u003cu\u003e他们诊断他患有 ABS\u003c/u\u003e\u003c/a\u003e，进行了抗真菌治疗。在药物不足以清除酵母菌，他的症状很快就复发了，血液酒精含量一度达到 0.4%。研究人员再次尝试了抗真菌治疗，这一次强度更大，直接通过导管注入静脉。2018 年 2 月，测试显示他的体内不再有酵母菌，他的饮食也都恢复了正常。\t\t\t\t\t                \u003c/div\u003e",
  "Date": "2019-10-27T14:43:02Z",
  "Author": "ai"
}