{
  "Source": "solidot",
  "Title": "数字文化重塑女性脸部",
  "Link": "https://www.solidot.org/story?sid=75071",
  "Content": "\u003cdiv class=\"p_mainnew\"\u003e\n\t\t\t\t\t过去几年，韩式审美理念逐渐推广到全球。韩国整容医生们早就考虑了全球主义，整容诊所在设计和持续调整算法，分析在审美上具有吸引力的脸孔，向客户推荐最优程序。算法测量了不同种族帅哥美女的比例，综合数据进行分析，发现全球所有种族的共同审美观。如今现代亚洲人的脸孔日益被韩国的审美标准所定义。人类非常擅长模仿，而互联网这个全球化舞台放大了这一切。\n韩式整容行业今天价值 100 亿美元，搭乘着韩流，它的规模只会越来越大。\u003cbr/\u003e\n\u003cp\u003e\u003c/p\u003e\n\u003c!--more--\u003e\n\u003cp\u003e\u003c/p\u003e\n\u003cbr/\u003e\nhttps://www.wired.com/story/flawless-korea-beauty-elise-hu/\t\t\t\t\t                \u003c/div\u003e",
  "Date": "2023-05-26T15:33:15Z",
  "Author": "Wilson"
}