{
  "Source": "solidot",
  "Title": "随着昆虫数量的减少植物花演化出自我授粉",
  "Link": "https://www.solidot.org/story?sid=76936",
  "Content": "\u003cdiv class=\"p_mainnew\"\u003e\n\t\t\t\t\t科学家发现，随着昆虫数量的减少，花逐渐放弃吸引传统授粉者，转而演化出自我授粉。生长在巴黎附近的三色堇（pansies）相比 20-30 年前的野生三色堇，花朵小了 10%，花蜜少了 20%，昆虫也很少光顾。植物为昆虫产生花蜜，昆虫的回报是帮助它们在彼此之间授粉。这种互惠关系是经历数百万年的共同演化发展而来的。但今天的三色堇与其昆虫授粉者之间出现了恶性循环：花蜜减少，昆虫也减少光顾。研究人员发现三色堇正朝着自我授粉演化，这在短期内有利但可能会限制其适应未来环境变化的能力。植物的演变如此之快令科学家感到吃惊。欧洲各地都报告昆虫数量在减少。德国自然保护区的一项研究发现，1989-2016 年落在陷阱中的昆虫总重量下降了 75%。此前研究发现，野生三色堇自我授粉比例过去 20 年增加了 25%。\n\u003cp\u003e\u003c/p\u003e\n\u003c!--more--\u003e\n\u003cp\u003e\u003c/p\u003e\n\u003cbr/\u003e\nhttps://www.theguardian.com/environment/2023/dec/20/flowers-giving-up-on-scarce-insects-and-evolving-to-self-pollinate-say-scientists\u003cbr/\u003e\t\t\t\t\t                \u003c/div\u003e",
  "Date": "2023-12-20T11:36:19Z",
  "Author": "Wilson"
}