{
  "Source": "solidot",
  "Title": "2019 年雨果奖公布",
  "Link": "https://www.solidot.org/story?sid=61762",
  "Content": "\u003cdiv class=\"p_mainnew\"\u003e\n\t\t\t\t\t在都柏林举办的第 77 届世界科幻大会公布了 2019 年雨果奖\u003ca href=\"https://dublin2019.com/wp-content/uploads/2019/08/201Hu@o%5Efulre@su@lt@s.pdf\"\u003e\u003cu\u003e评奖结果\u003c/u\u003e\u003c/a\u003e。\u003cbr/\u003e\n最佳长篇小说： Mary Robinette Kowal 的《\u003ca href=\"https://amzn.to/2ZdAzh9\"\u003e\u003cu\u003eThe Calculating Stars\u003c/u\u003e\u003c/a\u003e》，为《Lady Astronaut》系列的第一部，该书已获得 2019 年的星云奖和轨迹奖最佳长篇；\u003cbr/\u003e\n最佳中长篇小说：Martha Wells 的《\u003ca href=\"https://amzn.to/31Oq8Ch\" target=\"_blank\"\u003eArtificial Condition\u003c/a\u003e》；\u003cbr/\u003e\n最佳中短篇小说：Zen Cho 的《\u003ca href=\"https://www.barnesandnoble.com/blog/sci-fi-fantasy/if-at-first-you-dont-succeed-try-try-again-by-zen-cho/\" target=\"_blank\"\u003e\u003cu\u003eIf at First You Don’t Succeed, Try, Try Again\u003c/u\u003e\u003c/a\u003e》；\u003cbr/\u003e\n最佳短篇小说：Alix E. Harrow 的《\u003ca href=\"https://www.apex-magazine.com/a-witchs-guide-to-escape-a-practical-compendium-of-portal-fantasies/\" target=\"_blank\"\u003e\u003cu\u003eA Witch’s Guide to Escape: A Practical Compendium of Portal Fantasies\u003c/u\u003e\u003c/a\u003e》：\u003cbr/\u003e\n最佳系列小说：Becky Chambers 的《\u003ca href=\"https://www.amazon.com/gp/bookseries/B01E6Y33KY/ref=as_li_ss_tl?ie=UTF8\u0026amp;linkCode=sl2\u0026amp;tag=downandoutint-20\u0026amp;linkId=87a31a98d8b39e2135a9f1019b16f903\u0026amp;language=en_US\" target=\"_blank\"\u003e\u003cu\u003eWayfarers\u003c/u\u003e\u003c/a\u003e》系列；\u003cbr/\u003e\n最佳科幻电视：《The Good Place》之《\u003ca href=\"https://www.imdb.com/title/tt8578788/\"\u003e\u003cu\u003eJanet(s)\u003c/u\u003e\u003c/a\u003e》；\u003cbr/\u003e\n最佳科幻电影：《\u003ca href=\"https://www.imdb.com/title/tt4633694/\" target=\"_blank\"\u003e\u003cu\u003eSpider-Man: Into the Spider-Verse\u003c/u\u003e\u003c/a\u003e》。\t\t\t\t\t                \u003c/div\u003e",
  "Date": "2019-08-19T02:35:10Z",
  "Author": "wenfeixiang"
}