{
  "Source": "solidot",
  "Title": "世界最长寿者去世",
  "Link": "https://www.solidot.org/story?sid=71362",
  "Content": "\u003cdiv class=\"p_mainnew\"\u003e\n\t\t\t\t\t获吉尼斯世界纪录认证的“全球最长寿”老人\u003ca href=\"https://www.bbc.com/zhongwen/simp/world-61225556\"\u003e\u003cu\u003e去世\u003c/u\u003e\u003c/a\u003e，享年 119 岁。这名日本女性名为田中加子（Kane Tanaka），生于1903年，与乔治·奥威尔（George Orwell）同年。一个世纪前，她结了婚，生下了四个孩子。而她的晚年在日本一家养老院中度过。在那里，她喜欢玩棋盘游戏和吃巧克力。随着她的去世，118岁的法国修女露西尔·兰登（Lucile Randon）成为世界上最长寿的在世老人。在包括已去世的世界上最长寿老人记录中，法国女性珍妮·路易斯·卡尔芒（Jeanne Louise Calment）依然保持着记录。她于 1997 年去世，享年 122 岁 164 天。日本是世界上老年人口最多的国家。四分之一以上人口年龄在 65 岁或以上。\t\t\t\t\t                \u003c/div\u003e",
  "Date": "2022-04-26T07:18:20Z",
  "Author": "WinterIsComing"
}