{
  "Source": "solidot",
  "Title": "研究认为 2017 年美国青少年自杀率上升不是热播剧《十三个原因》导致的",
  "Link": "https://www.solidot.org/story?sid=73721",
  "Content": "\u003cdiv class=\"p_mainnew\"\u003e\n\t\t\t\t\t2017 年 3 月播出的《十三个原因第一季》讲述了一位少女自杀的故事。这部剧立即引发了争议，被认为会激发青少年中间的自杀模仿。这种现象被称为维特效应——以歌德小说《少年维特的烦恼》中的主人公名字命名。2019 年发表的一项研究分析了 2013 年 1 月 1 日到 2017 年 12 月 31 日期间 10-64 岁人群的自杀数据，发现自杀增长了 28.9%，其中男孩的自杀率在统计上显著增加，但女孩在统计上不具有显著性。在最新论文中，研究人员指出青少年自杀率有季节性模式，与学年相一致，在夏季出现下降。考虑到这一因素，2017 年该剧播出几个月后青少年自杀率上升可以用季节性因素解释，而不是模仿效应。\n\u003cp\u003e\u003c/p\u003e\n\u003c!--more--\u003e\n\u003cp\u003e\u003c/p\u003e\n\u003cbr/\u003e\nhttps://arstechnica.com/science/2022/12/study-2017-rise-in-teen-suicide-rates-due-to-seasonal-shifts-not-13-reasons-why/\t\t\t\t\t                \u003c/div\u003e",
  "Date": "2022-12-21T15:13:53Z",
  "Author": "Wilson"
}