{
  "Source": "solidot",
  "Title": "Meta 开源 Intermediate Graphics Library",
  "Link": "https://www.solidot.org/story?sid=75459",
  "Content": "\u003cdiv class=\"p_mainnew\"\u003e\n\t\t\t\t\tMeta 宣布开源 Intermediate Graphics Library（IGL）。IGL 为开发者提供了一组强大的工具为其应用创建高质量的视效和图形，能满足游戏、3D 建模等应用的需求。IGL 是一个跨平台图形库，支持 OpenGL、OpenGL ES、WebGL 和 Vulkan 等图形 API，它的开销小，外部依赖少。Meta 称 IGL 的特性包括：跨平台兼容，高性能渲染，易于使用的 API，可扩展，完全开源，可用于任何项目，没有任何许可限制。\n\u003cp\u003e\u003c/p\u003e\n\u003c!--more--\u003e\n\u003cp\u003e\u003c/p\u003e\n\u003cbr/\u003e\nhttps://www.khronos.org/blog/meta-uses-khronos-open-standards-in-new-intermediate-graphics-library\t\t\t\t\t                \u003c/div\u003e",
  "Date": "2023-07-08T11:21:11Z",
  "Author": "Wilson"
}