{
  "Source": "solidot",
  "Title": "Google Messages 应用将默认使用 RCS",
  "Link": "https://www.solidot.org/story?sid=75745",
  "Content": "\u003cdiv class=\"p_mainnew\"\u003e\n\t\t\t\t\tGoogle 宣布其 Messages 消息应用将默认使用 RCS，而 RCS 的群聊端对端加密将提供给所有用户。RCS 代表 Rich Communication Services，比短信或彩信支持更多的功能如群聊，能与采用 RCS 标准的运营商和厂商的消息应用兼容。Google 过去几年一直在致力于推广 RCS，但目前苹果的 iMessage 应用仍然不支持。Google 甚至建立了一个专门的网站试图说服苹果 iMessage 采用 RCS 标准。\n\u003cp\u003e\u003c/p\u003e\n\u003c!--more--\u003e\n\u003cp\u003e\u003c/p\u003e\n\u003cbr/\u003e\nhttps://techcrunch.com/2023/08/08/google-messages-will-now-use-rcs-by-default-and-encrypt-group-chats/\t\t\t\t\t                \u003c/div\u003e",
  "Date": "2023-08-09T06:58:01Z",
  "Author": "Wilson"
}