{
  "Source": "solidot",
  "Title": "台积电将在两个月内停止向华为供货",
  "Link": "https://www.solidot.org/story?sid=64969",
  "Content": "\u003cdiv class=\"p_mainnew\"\u003e\n\t\t\t\t\t针对美国限制华为的出口禁令，台积电周四在投资者电话会议上首度对外\u003ca href=\"http://www.ftchinese.com/story/001088576\"\u003e\u003cu\u003e表示\u003c/u\u003e\u003c/a\u003e，5 月 15 日已停止接受华为的新订单，除非美国核准，台积电预计在 9 月 14 日停止对华为出货。美国商务部在 5 月 15 日针对华为修改出口管制，任何厂商若使用美国设备或美国软件为华为设计或制造半导体晶片，都必须额外取得美国政府的出口许可证。这代表台积电和其他芯片厂，在没有许可证之下，不能对华为或其旗下晶片设计公司海思半导体出货。根据产业分析师的推估，华为目前为台积第二大客户、仅次于苹果，約占台积整体营收的一成四。台积电称，虽然有美国的出口禁令，5G 智能手机和高性能计算机处理器的强劲需求，其今年的收入预计\u003ca href=\"https://asia.nikkei.com/Spotlight/Huawei-crackdown/TSMC-plans-to-halt-chip-supplies-to-Huawei-in-2-months\"\u003e\u003cu\u003e能增长 20% 以上\u003c/u\u003e\u003c/a\u003e。\t\t\t\t\t                \u003c/div\u003e",
  "Date": "2020-07-17T04:41:53Z",
  "Author": "WinterIsComing"
}