{
  "Source": "solidot",
  "Title": "Reddit 月活跃用户数突破 4.3 亿",
  "Link": "https://www.solidot.org/story?sid=62856",
  "Content": "\u003cdiv class=\"p_mainnew\"\u003e\n\t\t\t\t\tReddit 官方博客在\u003ca href=\"https://redditblog.com/2019/12/04/reddits-2019-year-in-review/\"\u003e\u003cu\u003e年度总结\u003c/u\u003e\u003c/a\u003e中称，截至今年 10 月底，其用户人数较去年同期增长了 30%，月活跃用户\u003ca href=\"https://techcrunch.cn/2019/12/05/reddits-monthly-active-user-base-grew-30-to-reach-430m-in-2019/\"\u003e\u003cu\u003e达到了 4.3 亿\u003c/u\u003e\u003c/a\u003e。用户共发布了 1.99 亿则帖子和 17 亿条评论。去年，Reddit 报告称拥有 3.3 亿月活跃用户，数量超过了 Twitter。今年 2 月，Reddit 获腾讯领投 3 亿美元 D 轮融资，当时该网站被估值为 30 亿美元。用户担心这笔投资会影响 Reddit 内容，他们纷纷涌入 Reddit 并上传各种政治敏感图片。\t\t\t\t\t                \u003c/div\u003e",
  "Date": "2019-12-05T09:39:28Z",
  "Author": "WinterIsComing"
}