{
  "Source": "solidot",
  "Title": "Martin Shkreli 的武当派专辑被美国政府售出",
  "Link": "https://www.solidot.org/story?sid=68396",
  "Content": "\u003cdiv class=\"p_mainnew\"\u003e\n\t\t\t\t\tTuring Pharmaceuticals 制药公司前 CEO Martin Shkreli 因为大幅提高艾滋病治疗药物达拉匹林（Daraprim）的价格而成为美国互联网上的头号公敌。他在 2015 年 12 月因欺诈罪被捕，2017 年 8 月被定罪，2018 年法官做出裁决，没收 Martin Shkreli 的 736 万美元资产，包括一张据报道以 200 万美元购得的纽约饶舌乐队 “武当派” 的未公开发行专辑“\u003ca href=\"https://en.wikipedia.org/wiki/Once_Upon_a_Time_in_Shaolin\" target=\"_blank\"\u003e\u003cu\u003eOnce Upon a Time in Shaolin\u003c/u\u003e\u003c/a\u003e”。本周二，美国司法部\u003ca href=\"https://www.justice.gov/usao-edny/pr/united-states-sells-unique-wu-tang-clan-album-forfeited-convicted-hedge-fund-manager\"\u003e\u003cu\u003e披露\u003c/u\u003e\u003c/a\u003e它以未公开的价格将这张专辑\u003ca href=\"https://www.npr.org/2021/07/27/1021284593/martin-shkreli-wu-tang-clan-album-sold\" target=\"_blank\"\u003e\u003cu\u003e出售给了一位匿名买家\u003c/u\u003e\u003c/a\u003e。\t\t\t\t\t                \u003c/div\u003e",
  "Date": "2021-07-28T07:02:03Z",
  "Author": "WinterIsComing"
}