{
  "Source": "solidot",
  "Title": "台积电超过腾讯成为亚洲市值最高的企业",
  "Link": "https://www.solidot.org/story?sid=68597",
  "Content": "\u003cdiv class=\"p_mainnew\"\u003e\n\t\t\t\t\t世界最大的芯片代工厂台积电\u003ca href=\"https://www.cnbc.com/2021/08/18/taiwan-tsmc-valuation-overtakes-tencent-amid-chinas-tech-crackdown.html\" target=\"_blank\"\u003e\u003cu\u003e超过腾讯\u003c/u\u003e\u003c/a\u003e成为亚洲市值最高的企业。因过去一个多月监管方面对科技行业的打击，包括腾讯和阿里巴巴在内的主要互联网企业的股价出现巨幅振荡，腾讯的市值蒸发了\u003ca href=\"https://www.solidot.org/story?sid=68415\"\u003e\u003cu\u003e超过一千亿美元\u003c/u\u003e\u003c/a\u003e。截至周三台积电的市值为 5380 亿美元，超过腾讯的 5360 亿美元，第三是阿里巴巴的 4720 亿美元。在国家市场监管总局\u003ca href=\"https://www.solidot.org/story?sid=68579\"\u003e\u003cu\u003e公布\u003c/u\u003e\u003c/a\u003e《禁止网络不正当竞争行为规定（公开征求意见稿）》之后，腾讯和阿里巴巴的股价再遭重创，市值蒸发了超过 200 亿美元。\t\t\t\t\t                \u003c/div\u003e",
  "Date": "2021-08-19T00:56:19Z",
  "Author": "WinterIsComing"
}