{
  "Source": "solidot",
  "Title": "神舟十五号发射与空间站对接",
  "Link": "https://www.solidot.org/story?sid=73516",
  "Content": "\u003cdiv class=\"p_mainnew\"\u003e\n\t\t\t\t\t2022 年 11 月 29 日 23 时 08 分，搭载神舟十五号载人飞船的长征二号F遥十五运载火箭在酒泉卫星发射中心点火发射，约 10 分钟后，神舟十五号载人飞船与火箭成功分离，进入预定轨道。这是我国载人航天工程立项实施以来的第 27 次飞行任务，也是进入空间站阶段后的第 4 次载人飞行任务。11 月 30 日 5 时 42 分飞船成功对接于空间站天和核心舱前向端口，7 时 33 分，神舟十五号航天员乘组进入空间站，天宫空间站有了 6 名航天员，他们将共同生活五天，之后神舟十四号的三名航天员将搭乘飞船返回地面。\n\u003cp\u003e\u003c/p\u003e\n\u003c!--more--\u003e\n\u003cp\u003e\u003c/p\u003e\n\u003cbr/\u003e\nhttp://www.cmse.gov.cn/xwzx/202211/t20221129_51683.html\u003cbr/\u003e\nhttp://www.cmse.gov.cn/xwzx/202211/t20221130_51695.html\t\t\t\t\t                \u003c/div\u003e",
  "Date": "2022-11-30T04:48:07Z",
  "Author": "Wilson"
}