{
  "Source": "solidot",
  "Title": "为迎接热浪德州加密货币矿工关闭矿机",
  "Link": "https://www.solidot.org/story?sid=72104",
  "Content": "\u003cdiv class=\"p_mainnew\"\u003e\n\t\t\t\t\t为迎接热浪来临及其可能导致的电力供应紧张，美国德克萨斯州几乎所有工业规模的比特币矿工\u003ca href=\"https://www.bloomberg.com/news/articles/2022-07-11/bitcoin-miners-shut-off-rigs-as-texas-power-grid-nears-brink\" target=\"_blank\"\u003e\u003cu\u003e都关闭了矿机\u003c/u\u003e\u003c/a\u003e。因为德州便宜的电力且对加密货币挖矿宽松的政策，Riot Blockchain、Argo Blockchain 和 Core Scientific 等运营数百万台矿机的比特币挖矿公司涌向了该州。比特币挖矿需要消耗大量电力。德州也一跃成为世界最大的比特币挖矿中心之一。按照德州电网运营组织 The Electric Reliability Council of Texas, Inc.(\u003ca href=\"https://www.ercot.com/\"\u003eERCOT\u003c/a\u003e)的要求，关闭矿机之后有逾 1000 兆瓦的比特币挖矿负荷可用于电网的重新分配，这代表了德州所有工业规模的比特币挖矿负荷。因最近比特币价格下降，矿工们已面临利润下滑。\t\t\t\t\t                \u003c/div\u003e",
  "Date": "2022-07-12T14:26:42Z",
  "Author": "WinterIsComing"
}