{
  "Source": "solidot",
  "Title": "研究显示高研发成本不能解释高药品价格",
  "Link": "https://www.solidot.org/story?sid=73004",
  "Content": "\u003cdiv class=\"p_mainnew\"\u003e\n\t\t\t\t\t药物专利的捍卫者多年来一直宣称需要专利和高药品价格是因为新药研发成本高。但事实上新药研发成本很大一部分是由政府（也就是纳税人）资助的，而根据发表在《JAMA Network Open》上的\u003ca href=\"https://jamanetwork.com/journals/jamanetworkopen/fullarticle/2796669\"\u003e\u003cu\u003e一项研究\u003c/u\u003e\u003c/a\u003e，研发成本和高药价之间是不相关的。研究人员对比了新药的研发成本和出售价格，发现两者没有关联，药品的治疗价值也与价格不相关。研究人员发现药厂不是根据药物的研发成本或质量定价的，\u003ca href=\"https://www.techdirt.com/2022/10/03/new-study-shows-that-high-rd-costs-dont-explain-high-drug-prices/\"\u003e而是根据市场能承受的费用\u003c/a\u003e。\t\t\t\t\t                \u003c/div\u003e",
  "Date": "2022-10-10T07:25:28Z",
  "Author": "WinterIsComing"
}