{
  "Source": "solidot",
  "Title": "厄瓜多尔记者收到插入电脑会爆炸的 U 盘",
  "Link": "https://www.solidot.org/story?sid=74470",
  "Content": "\u003cdiv class=\"p_mainnew\"\u003e\n\t\t\t\t\t五名厄瓜多尔记者收到了激活时会爆炸的 U 盘。瓜亚基尔 Ecuavisa 电视台记者 Lenin Artieda 在收到 U 盘后将其插入电脑，这时 U 盘发生了爆炸。记者的手和脸部受到了轻伤，没有其他人受到伤害。U 盘内被认为装有名为环三亚甲基三硝胺（RDX）的高能炸药，该炸药也被美国军方使用，可以单独用也可以与 TNT 等炸药混合。Artieda 插入的 U 盘只有半数炸药激活，因此可能产生的伤害较小。厄瓜多尔非盈利组织 Fundamedios 称另外还有两名瓜亚基尔和两名首都的记者收到了炸弹 U 盘。EXA FM 电台记者 Alvaro Rosero 在 3 月 15 日收到了装有 U 盘的信件，他将其交给了一位制片人，后者使用带适配器的线缆将其连接到电脑上，U 盘没有爆炸，警方认为是适配器没有足够的电量激活炸弹。警方对其它 U 盘实施了“控制性引爆”。目前还不清楚邮寄炸弹 U 盘的动机，厄瓜多尔内政部长 Juana Zapata 表示邮寄者旨在传达让记者闭嘴的信息。政府表示，任何企图恐吓新闻和言论自由的行为都应该收到严厉的司法惩罚。\n\u003cp\u003e\u003c/p\u003e\n\u003c!--more--\u003e\n\u003cp\u003e\u003c/p\u003e\n\u003cbr/\u003e\nhttps://arstechnica.com/?p=1925950\t\t\t\t\t                \u003c/div\u003e",
  "Date": "2023-03-23T07:26:16Z",
  "Author": "Wilson"
}