{
  "Source": "solidot",
  "Title": "罕见爱因斯坦手稿在巴黎拍卖",
  "Link": "https://www.solidot.org/story?sid=69719",
  "Content": "\u003cdiv class=\"p_mainnew\"\u003e\n\t\t\t\t\t爱因斯坦通常会扔掉他颠覆性工作的手稿。感谢他的同事和友人，一份工作手稿奇迹般的保存至今，\u003ca href=\"https://www.washingtonpost.com/world/2021/11/22/einstein-manuscript-auction/\" target=\"_blank\"\u003e\u003cu\u003e将于周二在巴黎拍卖\u003c/u\u003e\u003c/a\u003e，预计拍卖价格在 200 万到 300 万欧元之间。代表 Aguttes 拍卖行的佳士得称，这份 54 页的工作手稿由爱因斯坦及其友人、瑞士工程师 Michele Besso 合作手写，书写年代在 1913  到 1914 年之间，记录了广义相对论的准备工作，其中 26 页来自爱因斯坦，25 页来自 Besso，另外 3 页含有两人的条目。\t\t\t\t\t                \u003c/div\u003e",
  "Date": "2021-11-23T07:17:15Z",
  "Author": "WinterIsComing"
}