{
  "Source": "solidot",
  "Title": "研究称猫有近 300 种面部表情",
  "Link": "https://www.solidot.org/story?sid=76511",
  "Content": "\u003cdiv class=\"p_mainnew\"\u003e\n\t\t\t\t\t对狗、黑猩猩和人类的面部表情的研究发现。人类有 44 种面部表情，犬科动物有 27 种，黑猩猩有 357 种，但对猫的面部表情的研究却少之又少。在过去一年里，阿肯色州里昂学院心理学助理教授 Brittany Florkiewicz 等人记录了在洛杉矶一家猫咖啡馆生活的 50 只猫的 276 种不同的面部表情。根据这项研究，猫的每种表情都包含了 26 种独特面部动作中的 4 种左右，包括嘴唇张开、瞳孔扩张或收缩、眨眼、舔鼻子和耳朵的不同位置。研究人员得出结论称，猫科动物 45% 的表情是友好的，37% 的表情是攻击性的。研究人员表示，还需要开展更多研究来确切地了解这些猫对彼此“说”了什么，但他们希望动物收容机构能够利用这一研究来更好地评估他们照顾的猫。目前已有公司联系他们，希望设计一款应用，让人们记录并解码猫的面部表情。\n\u003cp\u003e\u003c/p\u003e\n\u003c!--more--\u003e\n\u003cp\u003e\u003c/p\u003e\n\u003cbr/\u003e\nhttps://www.livescience.com/animals/cats/cats-have-nearly-300-facial-expressions-including-a-play-face-they-share-with-humans\u003cbr/\u003e\nhttps://news.sciencenet.cn/htmlnews/2023/11/511515.shtm\t\t\t\t\t                \u003c/div\u003e",
  "Date": "2023-11-02T07:46:53Z",
  "Author": "Wilson"
}