{
  "Source": "solidot",
  "Title": "特朗普政府督促芯片公司在美国建厂",
  "Link": "https://www.solidot.org/story?sid=64323",
  "Content": "\u003cdiv class=\"p_mainnew\"\u003e\n\t\t\t\t\t特朗普政府正与半导体公司\u003ca href=\"https://cn.reuters.com/article/trump-chipmakers-discussion-0510-sun-idCNKBS22N00P\" target=\"_blank\"\u003e\u003cu\u003e商讨在美国建厂\u003c/u\u003e\u003c/a\u003e。英特尔发言人在一份电子邮件声明中表示，英特尔正与美国国防部就改善微电子及相关技术的国内来源进行讨论，“英特尔已做好准备与美国政府合作运营一家美国自家的晶圆代工厂，并提供各种安全的微电子产品”。另一方面，台积电在与美国商务部商讨在美建厂事宜，但该公司称尚未做出最终决定。“我们正在积极评估所有合适的地点，包括在美国的地点，但还没有具体计划，”台积电发言人高孟华在声明中称。美国官员还在考虑帮助韩国三星扩大在美国的代工业务。三星在得州奥斯丁有芯片工厂。\t\t\t\t\t                \u003c/div\u003e",
  "Date": "2020-05-11T05:58:35Z",
  "Author": "WinterIsComing"
}