{
  "Source": "solidot",
  "Title": "Unicode Emoji 13.0 将引入 62 个全新的绘文字",
  "Link": "https://www.solidot.org/story?sid=63403",
  "Content": "\u003cdiv class=\"p_mainnew\"\u003e\n\t\t\t\t\tUnicode 联盟官方博客\u003ca href=\"http://blog.unicode.org/2020/01/unicode-emoji-130-now-final-for-2020.html\"\u003e\u003cu\u003e宣布\u003c/u\u003e\u003c/a\u003e，Unicode Emoji 13.0 已经确定下来，将随计划于 3 月释出的 Unicode 13.0 一起发布，用户预计到 9 月/10 月会在手机上使用到这些新的绘文字——虽然有行业标志，但厂商会推出自己的定制风格版本。Unicode 标准现在一年发布一个版本，Emoji 13.0 增加了 62 个全新绘文字，以及 55 个性别和肤色变化，绘文字总数增加到了\u003ca href=\"https://unicode.org/emoji/charts-13.0/emoji-counts.html\"\u003e\u003cu\u003e 3304 个\u003c/u\u003e\u003c/a\u003e。这些新绘文字包括了泪笑，北极熊，珍珠奶茶，皮卡，火锅，跨性别旗帜等等。\t\t\t\t\t                \u003c/div\u003e",
  "Date": "2020-02-03T07:56:21Z",
  "Author": "WinterIsComing"
}