{
  "Source": "solidot",
  "Title": "今日头条等应用被指超范围采集公民个人隐私",
  "Link": "https://www.solidot.org/story?sid=62085",
  "Content": "\u003cdiv class=\"p_mainnew\"\u003e\n\t\t\t\t\t国家计算机病毒中心\u003ca href=\"http://www.nbd.com.cn/articles/2019-09-16/1371816.html\"\u003e\u003cu\u003e发布了\u003c/u\u003e\u003c/a\u003e《移动 APP 违法违规问题及治理举措》（官网未找到），公布了存在的六大类问题的 APP 和 SDK，这些问题包括包括远程控制、恶意扣费等八大类恶意行为、涉嫌侵犯公民个人隐私、涉嫌超范围采集公民个人隐私等。MOMO 陌陌（版本 8.18.7）、今日头条（版本 7.2.7）、京东金融 （版本: 5.2.32）、云闪付（版本: 6.2.6）都被指存在超范围采集公民个人隐私的问题。\t\t\t\t\t                \u003c/div\u003e",
  "Date": "2019-09-16T05:03:25Z",
  "Author": "wenfeixiang"
}