{
  "Source": "solidot",
  "Title": "中国实验性熔盐反应堆获得运营许可",
  "Link": "https://www.solidot.org/story?sid=75337",
  "Content": "\u003cdiv class=\"p_mainnew\"\u003e\n\t\t\t\t\t位于甘肃省武威市的 2MWt 液态燃料钍基熔盐实验堆(TMSR-LF1)已获得由国家核安全局颁发的运行许可证。根据现行核安全法规，获取运行许可证后，实验堆即可进行首次装料，由此进入“带核运行”状态。但在装料后，核工程还必须经历一系列调试和试运行过程，正式运行仍需时日。如果 TMSR-LF1 取得成功，中国计划到 2030 年建造一座装机容量 373MWt 的熔盐反应堆。相比传统的铀反应堆，钍的储存量更丰富，而中国的钍储藏量位居世界前列。钍基反应堆产生的核废料也更少，使用熔盐作为燃料和冷却剂也有助于减少对大量水的需求，可以在水资源缺乏的地区建造反应堆。TMSR-LF1 于 2018 年开工建设，主体工程于 2021 年完工。\n\u003cp\u003e\u003c/p\u003e\n\u003c!--more--\u003e\n\u003cp\u003e\u003c/p\u003e\n\u003cbr/\u003e\nhttps://www.scmp.com/news/china/science/article/3224183/china-gives-green-light-nuclear-reactor-burns-thorium-fuel-could-power-country-20000-years\t\t\t\t\t                \u003c/div\u003e",
  "Date": "2023-06-26T05:33:00Z",
  "Author": "Wilson"
}