{
  "Source": "solidot",
  "Title": "新冠重症患者会产生抗体损害自身血压调节",
  "Link": "https://www.solidot.org/story?sid=73134",
  "Content": "\u003cdiv class=\"p_mainnew\"\u003e\n\t\t\t\t\t\u003ca href=\"mailto:firedragonksd@126.com\"\u003e诸葛恐民\u003c/a\u003e 写道\u003ci\u003e \u0026#34;\u003cspan\u003e\n新冠重症患者会自发产生与血压失调和疾病严重程度相关的AngII（血管紧张素II）抗体。芝加哥大学的研究者们\u003ca href=\"https://www.science.org/doi/10.1126/sciadv.abn3777\"\u003e发现\u003c/a\u003e，有相当一部分因新冠住院的患者产生了AngII\u003cspan style=\"font-size: unset; color: unset; font-family: unset;\"\u003e抗体。新冠病毒的靶蛋白是ACE2（血管紧张素转换酶2），而AngII经ACE2加工为升压素来调节血压。新冠病毒的Spike或RBD蛋白引起的特异免疫反应可诱导Ang2抗体，说明AngII与Spike/RBD蛋白存在某些抗原表位模拟（即均可与ACE2结合）。这项研究为解释新冠病毒免疫反应如何损害血压调节提供了重要见解。\u003c/span\u003e\n\u003c/span\u003e\n\u0026#34;\u003c/i\u003e\t\t\t\t\t                \u003c/div\u003e",
  "Date": "2022-10-21T16:02:32Z",
  "Author": "WinterIsComing"
}