{
  "Source": "solidot",
  "Title": "新冠重症化的原因",
  "Link": "https://www.solidot.org/story?sid=64335",
  "Content": "\u003cdiv class=\"p_mainnew\"\u003e\n\t\t\t\t\t根据美国疾病控制与预防中心（CDC）最近公布的关于超过 7100 名患者健康状况的报告，在基础疾病当中，心脏病等心血管疾病患者的约 6 成、糖尿病患者的约 5 成需要住院或进入重症监护室（ICU）治疗。没有基础疾病的人群 8 成以上未住院，再次印证患有基础疾病者容易发展成重症。已有研究结果表明新冠病毒\u003ca href=\"http://cn.nikkei.com/industry/scienceatechnology/40509-2020-05-12-04-41-00.html\" target=\"_blank\"\u003e容易与 ACE2 结合\u003c/a\u003e。位于细胞表面的受体蛋白质 ACE2 广泛存在于心肺肾等部位，新冠病毒感染时先与 ACE2 结合然后侵入细胞。由于基础疾病和吸烟的影响，器官等细胞表面的 ACE2 的数量等会发生变化。欧洲疾病预防控制中心（ECDC）指出，由于 ACE2 会因为吸烟而被激活，如果吸烟者感染新冠，有可能会发展为重症。\t\t\t\t\t                \u003c/div\u003e",
  "Date": "2020-05-12T06:33:37Z",
  "Author": "ai"
}