{
  "Source": "solidot",
  "Title": "NASA 准备修复哈勃望远镜的问题",
  "Link": "https://www.solidot.org/story?sid=68291",
  "Content": "\u003cdiv class=\"p_mainnew\"\u003e\n\t\t\t\t\t哈勃望远镜因为负荷计算机故障已经处于“安全模式”一个多月，故障的可能源头已被跟踪到一个向故障计算机供电的控制单元，地面控制人员\u003ca href=\"https://www.bbc.com/news/science-environment-57844454\" target=\"_blank\"\u003e\u003cu\u003e准备切换到备份硬件\u003c/u\u003e\u003c/a\u003e。NASA 表示望远镜本身以及科学仪器的状况都是良好的。在这之前，地面控制人员已经发送指令重置被认为存在问题的电源控制单元，但这一尝试失败了。NASA 现在批准哈勃故障修复团队切换到备份的电源控制单元，将在美国时间周四开始实施。\t\t\t\t\t                \u003c/div\u003e",
  "Date": "2021-07-15T08:33:35Z",
  "Author": "WinterIsComing"
}