{
  "Source": "solidot",
  "Title": "Red Hat 限制源码的决定引发愤怒和同情",
  "Link": "https://www.solidot.org/story?sid=75538",
  "Content": "\u003cdiv class=\"p_mainnew\"\u003e\n\t\t\t\t\tRed Hat 最近限制了其企业发行版 RHEL（Red Hat Enterprise Linux）源码的可得性，这一决定既引发愤怒也引发了同情。引发同情的主要原因是它的竞争对手如甲骨文以及社区发行版 Alma Linux 和 Rocky Linux 都是直接克隆了 Red Hat 的工作成果。但迫使克隆产品退出并不能将他们的客户转变成 Red Hat 的客户，Red Hat 的商业方案小企业是承担不起的。部分人怀疑此举是 IBM 施压的结果，但 Red Hat 早在被 IBM 收购前就将它自己收购的社区发行版项目 CentOS 变成了滚动更新发行版 CentOS Stream，直接导致了社区发行版 Alma Linux 和 Rocky Linux 的诞生。目前的初步结果是 Red Hat 的最新决定提升了这些社区发行版的知名度和活力。\n\u003cp\u003e\u003c/p\u003e\n\u003c!--more--\u003e\n\u003cp\u003e\u003c/p\u003e\n\u003cbr/\u003e\nhttps://linux.slashdot.org/story/23/07/15/0138208/red-hats-decision-prompts-outrage-and-sympathy-called-necessary-and-embarrassing\t\t\t\t\t                \u003c/div\u003e",
  "Date": "2023-07-17T14:19:38Z",
  "Author": "Wilson"
}