{
  "Source": "solidot",
  "Title": "Google Mandiant 发现证据显示黑客与俄罗斯协同攻击",
  "Link": "https://www.solidot.org/story?sid=72881",
  "Content": "\u003cdiv class=\"p_mainnew\"\u003e\n\t\t\t\t\tGoogle 最近以 54 亿美元收购的安全公司 Mandiant 报告发现证据\u003ca href=\"https://cn.wsj.com/articles/%E8%B0%B7%E6%AD%8C%E8%A7%82%E5%AF%9F%E5%88%B0%E4%BF%84%E7%BD%97%E6%96%AF%E4%B8%8E%E9%BB%91%E5%AE%A2%E5%8D%8F%E5%90%8C%E5%AE%9E%E6%96%BD%E6%B6%89%E5%8F%8A%E4%BF%84%E4%B9%8C%E6%88%98%E4%BA%89%E7%9A%84%E7%BD%91%E7%BB%9C%E6%94%BB%E5%87%BB-11663984806\" target=\"_blank\"\u003e\u003cu\u003e显示\u003c/u\u003e\u003c/a\u003e黑客与俄罗斯协同攻击。安全研究人员观察到，支持俄罗斯的黑客组织（表面上由爱国的公民黑客组成）与俄罗斯军事情报机构(GRU)的网络入侵活动之间存在明显的协作。Mandiant 称，在四起网络攻击事件中观察到了与 GRU 有关的黑客活动，在这些活动中，恶意 Wiper 软件被安装到了一个受害者的网络上。Mandiant 称，有三个支持俄罗斯的黑客组织参与其中，它们被称为 XakNet Team、Infoccentr 和 CyberArmyofRussia_Reborn。\t\t\t\t\t                \u003c/div\u003e",
  "Date": "2022-09-26T09:36:35Z",
  "Author": "WinterIsComing"
}