{
  "Source": "solidot",
  "Title": "AirPods 是目前苹果增长最快的产品",
  "Link": "https://www.solidot.org/story?sid=63198",
  "Content": "\u003cdiv class=\"p_mainnew\"\u003e\n\t\t\t\t\t苹果的旗舰手机 iPhone 的销量在下滑，但手机配件 AirPods 无线耳机却出人意料的\u003ca href=\"https://apple.slashdot.org/story/20/01/07/236207/apple-airpods-make-more-money-than-spotify-twitter-snapchat-and-shopify-combined\" target=\"_blank\"\u003e\u003cu\u003e连续三年获得高速增长\u003c/u\u003e\u003c/a\u003e。2017 年，苹果售出了 1500 万 AirPods；2018 年销量翻番至 3500 万；2019 年销量接近再次翻番，估计售出 6000 万双，而产品的价格也从之前的 150 美元增加到 200 或 250 美元（AirPods Pro）。2019 年苹果 AirPods 的收入可能达到了 120 亿美元，相当于 iPhone 收入的 4.5%，比 Spotify、Twitter、Snap 和 Shopify 加起来还要多。\t\t\t\t\t                \u003c/div\u003e",
  "Date": "2020-01-08T04:46:26Z",
  "Author": "WinterIsComing"
}