{
  "Source": "solidot",
  "Title": "上不了网课的孩子",
  "Link": "https://www.solidot.org/story?sid=63853",
  "Content": "\u003cdiv class=\"p_mainnew\"\u003e\n\t\t\t\t\t尽管中国经济近几十年来取得了长足发展，但仍有很大一部分人缺少网上生活所需的基本条件——智能手机和可靠的互联网。在新冠病毒将网上的便利变成了生活必需品的时候，这些大多生活在中国农村腹地的人们与他们日常生活的联系已经被切断，\u003ca href=\"https://cn.nytimes.com/technology/20200318/china-schools-coronavirus/\"\u003e尤其是在教育方面\u003c/a\u003e。新冠病毒疫情对富人和穷人、城市和农村迥然不同的影响，是世界上越来越多的其他地区正迅速开始面对的一个现实。中国有许多父母买不起多部智能手机，供自己和孩子使用，尽管世界上许多最便宜的智能手机——以及大多数最高档的智能手机——都是中国制造的。虽然 4G 网络已覆盖了中国，但农村部分地区的信号较差。在大城市以外的地方，家庭宽带入网可能也很贵。据中国新闻报道，一些地方的学生要徒步数小时，冒着严寒爬到山顶去上网课，因为那是他们能获得良好手机信号的唯一地方。有人看到四川省的一名高中生在崖壁边蹭网上课。\t\t\t\t\t                \u003c/div\u003e",
  "Date": "2020-03-18T06:15:09Z",
  "Author": "WinterIsComing"
}