{
  "Source": "solidot",
  "Title": "哈工大等高校被禁止使用 MATLAB",
  "Link": "https://www.solidot.org/story?sid=64640",
  "Content": "\u003cdiv class=\"p_mainnew\"\u003e\n\t\t\t\t\t哈工大过去两年\u003ca href=\"http://today.hit.edu.cn/articles?tags=MATLAB\"\u003e\u003cu\u003e上线了\u003c/u\u003e\u003c/a\u003e正版的数学软件 MATLAB（校园版），但过去几天哈工大的教师和学生反应因为哈工大被列入了美国的出口禁止名单，MATLAB 的开发商 MathWorks 停止向哈工大继续提供服务，软件显示激活失效。这一事件在社交媒体上引发了广泛的\u003ca href=\"https://www.zhihu.com/question/400551624\"\u003e\u003cu\u003e争议\u003c/u\u003e\u003c/a\u003e。根据美国商务部的通知，北京航空航天大学、中国人民大学、国防科技大学、湖南大学、哈尔滨工业大学、哈尔滨工程大学、西北工业大学、西安交通大学、电子科技大学、四川大学、同济大学、广东工业大学以及南昌大学等 13 所大学列入了最新的“实体名单”。\t\t\t\t\t                \u003c/div\u003e",
  "Date": "2020-06-12T00:03:28Z",
  "Author": "WinterIsComing"
}