{
  "Source": "solidot",
  "Title": "考古学家在印尼发现有 4.5 万年历史的洞穴画像",
  "Link": "https://www.solidot.org/story?sid=66708",
  "Content": "\u003cdiv class=\"p_mainnew\"\u003e\n\t\t\t\t\t考古学家在印尼\u003ca href=\"https://www.bbc.com/ukchina/simp/55724238\"\u003e发现了\u003c/a\u003e世界上迄今最古老的洞穴动物画——一头野猪，它至少有 4.55 万年的历史。\u003ca href=\"https://advances.sciencemag.org/content/7/3/eabd4648\"\u003e\u003cu\u003e研究报告\u003c/u\u003e\u003c/a\u003e发表在《Science Advances》期刊上。发现这幅画的地方位于印尼苏拉威西岛一个偏远山谷中的洞穴。它提供了该地区人类定居的最早证据。这幅画长 136 厘米、宽 54 厘米，描绘的是成年苏拉威西疣猪的样子。猪背上方有两个手印， 附近应该还有另外两头猪，但它们只留存下一部分。研究人员表示，岩壁上的那两个手印在制作时，是创作者将手放在壁上，然后再将颜料吐在周围而成，因此考古团队希望能够提取到颜料中唾液留下的 DNA 样本。\n\t\t\t\t\t                \u003c/div\u003e",
  "Date": "2021-01-20T06:07:14Z",
  "Author": "WinterIsComing"
}