{
  "Source": "solidot",
  "Title": "国际能源署报告到 2050 年核电装机容量翻一番才能实现零排放",
  "Link": "https://www.solidot.org/story?sid=72011",
  "Content": "\u003cdiv class=\"p_mainnew\"\u003e\n\t\t\t\t\t国际能源署发表\u003ca href=\"https://www.iea.org/reports/nuclear-power-and-secure-energy-transitions\"\u003e\u003cu\u003e报告\u003c/u\u003e\u003c/a\u003e《Nuclear Power and Secure Energy Transitions: From Today’s Challenges to Tomorrow’s Clean Energy Systems》，认为为了到本世纪中叶实现净零排放，全球的核电装机容量\u003ca href=\"https://hardware.slashdot.org/story/22/06/30/2236252/iea-global-nuclear-power-capacity-must-double-by-2050-to-reach-net-zero-emissions\"\u003e\u003cu\u003e需要翻一番\u003c/u\u003e\u003c/a\u003e，从今天的 413 GW 增加到 812 GW，2030 年代的年核电装机容量需要增加 27 GW。如此才有机会将全球的气温上升控制在比工业化前水平高 1.5 摄氏度。此外目前占到全球装机容量 63% 或 260 GW 的核电站其历史已经逾 30 年，接近其寿命终点。发达国家的核电装机容量到 2030 年可能会因为寿命到期而缩小三分之一。发达经济体的核电装机容量占到了全球的七成，但核电机组在老化，没有多少新核电站在投资建造。\t\t\t\t\t                \u003c/div\u003e",
  "Date": "2022-07-02T11:33:42Z",
  "Author": "WinterIsComing"
}