{
  "Source": "liam.page",
  "Title": "互联网下半场对个人而言意味着什么？",
  "Link": "https://liam.page/2016/11/27/brief-think-of-the-last-half-of-Internet-time/",
  "Content": "\u003cdiv class=\"post-body\" itemprop=\"articleBody\"\u003e\n\n      \n        \u003cp\u003e互联网的人口红利已经结束了，上半场的粗犷增长已经结束，可以算是进入下半场了。所以我在想，这个下半场对于个人而言，意味着什么。\u003c/p\u003e\n\u003cspan id=\"more\"\u003e\u003c/span\u003e\n\n\u003cp\u003e对于商家而言，最好挣的钱是信息不对称带来的；与之对应，对于个人而言，会最惨的结局，也会是因为信息不对称。举个栗子，过去，人们去中关村买东西，会被骗，中关村被称为骗子一条街；会被骗，就是因为信息不对称：这种不对称是因为不懂电脑，但更重要的是不知道别的顾客对东西的评价。后来有了电商，这种不对称就消失了；因为所有的评价都公开透明了：你买东西，所有曾经买过这个东西的人，都有评价。好的就点赞，差的就骂娘。这些所有的一切，你都能看到。\u003c/p\u003e\n\u003cp\u003e那么时代发展到这里，接下来的信息不对称，会以怎样的方式呈现出来呢？我觉得这件事情就变得很重要了。掌握了这件事情，就能成事，能挣钱；对于个人而言，就能避免悲惨的结局。今天我看到消息，讲Google 的 DeepMind 团队，和剑桥大学合作，搞了个「唇语识别 AI」。这个项目，轻轻松松，就秒杀了多年训练的人类唇语阅读专家，准确率是翻倍的提升。DeepMind 只是「稍稍尝试了一下」，就完成了这样的工作。于是我有感触，互联网下半场对于个人而言，信息不对称以另外的方式呈现：不善于学习和不敢于尝试新东西的人会在这波被落下，边缘化，然后彻底被抛弃。也就是说，因为互联网的信息传递能力，社会的平均信息水平提高；但与之相对应的，个人信息水平与对事物的接触早晚程度关系不大，主要决定于个人的学习能力。郑渊洁前段时间在演讲里说，「时代已经从『隔行如隔山』发展到了『隔行可登山』」，深以为然。\u003c/p\u003e\n\u003cp\u003e所以结论是：如果一个人，不善于学习、不敢于尝试，在接下来的时代，会死得很惨。\u003c/p\u003e\n\n    \u003c/div\u003e",
  "Date": "2016-11-27T12:51:13Z",
  "Author": "Liam Huang"
}